JianZhiOfferZhuanxiangTujiBanQuanjieDoocsKaiyuanShequFix1/README.md
JianZhiOfferZhuanxiangTujiBanQuanjieDoocsKaiyuanShequFix1/__init__.py
JianZhiOfferZhuanxiangTujiBanQuanjieDoocsKaiyuanShequFix1/__main__.py
JianZhiOfferZhuanxiangTujiBanQuanjieDoocsKaiyuanShequFix1/file.epub
JianZhiOfferZhuanxiangTujiBanQuanjieDoocsKaiyuanShequFix1/index.html
JianZhiOfferZhuanxiangTujiBanQuanjieDoocsKaiyuanShequFix1/css/__init__.py
JianZhiOfferZhuanxiangTujiBanQuanjieDoocsKaiyuanShequFix1/css/annotations.css
JianZhiOfferZhuanxiangTujiBanQuanjieDoocsKaiyuanShequFix1/css/main.css
JianZhiOfferZhuanxiangTujiBanQuanjieDoocsKaiyuanShequFix1/css/normalize.css
JianZhiOfferZhuanxiangTujiBanQuanjieDoocsKaiyuanShequFix1/css/popup.css
JianZhiOfferZhuanxiangTujiBanQuanjieDoocsKaiyuanShequFix1/font/__init__.py
JianZhiOfferZhuanxiangTujiBanQuanjieDoocsKaiyuanShequFix1/font/fontello.eot
JianZhiOfferZhuanxiangTujiBanQuanjieDoocsKaiyuanShequFix1/font/fontello.svg
JianZhiOfferZhuanxiangTujiBanQuanjieDoocsKaiyuanShequFix1/font/fontello.ttf
JianZhiOfferZhuanxiangTujiBanQuanjieDoocsKaiyuanShequFix1/font/fontello.woff
JianZhiOfferZhuanxiangTujiBanQuanjieDoocsKaiyuanShequFix1/img/__init__.py
JianZhiOfferZhuanxiangTujiBanQuanjieDoocsKaiyuanShequFix1/img/annotator-glyph-sprite.png
JianZhiOfferZhuanxiangTujiBanQuanjieDoocsKaiyuanShequFix1/img/annotator-icon-sprite.png
JianZhiOfferZhuanxiangTujiBanQuanjieDoocsKaiyuanShequFix1/img/apple-touch-icon.png
JianZhiOfferZhuanxiangTujiBanQuanjieDoocsKaiyuanShequFix1/img/cancelfullscreen.png
JianZhiOfferZhuanxiangTujiBanQuanjieDoocsKaiyuanShequFix1/img/close.png
JianZhiOfferZhuanxiangTujiBanQuanjieDoocsKaiyuanShequFix1/img/fullscreen.png
JianZhiOfferZhuanxiangTujiBanQuanjieDoocsKaiyuanShequFix1/img/loader.gif
JianZhiOfferZhuanxiangTujiBanQuanjieDoocsKaiyuanShequFix1/img/menu-icon.png
JianZhiOfferZhuanxiangTujiBanQuanjieDoocsKaiyuanShequFix1/img/save.png
JianZhiOfferZhuanxiangTujiBanQuanjieDoocsKaiyuanShequFix1/img/saved.png
jian_zhi_offer_zhuanxiang_tuji_ban_quanjie_doocs_kaiyuan_shequ_fix1-2025.3.25.1.dist-info/METADATA
jian_zhi_offer_zhuanxiang_tuji_ban_quanjie_doocs_kaiyuan_shequ_fix1-2025.3.25.1.dist-info/WHEEL
jian_zhi_offer_zhuanxiang_tuji_ban_quanjie_doocs_kaiyuan_shequ_fix1-2025.3.25.1.dist-info/entry_points.txt
jian_zhi_offer_zhuanxiang_tuji_ban_quanjie_doocs_kaiyuan_shequ_fix1-2025.3.25.1.dist-info/top_level.txt
jian_zhi_offer_zhuanxiang_tuji_ban_quanjie_doocs_kaiyuan_shequ_fix1-2025.3.25.1.dist-info/RECORD
